c2net/__init__.py
c2net/context/__init__.py
c2net/context/context.py
c2net/context/download.py
c2net/context/moxing_env_check.py
c2net/context/moxing_helper.py
c2net/context/upload.py
c2net/utils/__init__.py
c2net/utils/constants.py
c2net/utils/util.py
c2net-0.2.0.post3.dist-info/METADATA
c2net-0.2.0.post3.dist-info/WHEEL
c2net-0.2.0.post3.dist-info/top_level.txt
c2net-0.2.0.post3.dist-info/RECORD
