Metadata-Version: 2.1
Name: c2net
Version: 0.2.0.post3
Summary: A package for c2net pypi
Home-page: https://openi.pcl.ac.cn/OpenIOSSG/c2net-pypi
Author: liuzx
Author-email: gsunfeng@163.com
License: MIT
Classifier: License :: OSI Approved :: MIT License
Classifier: Intended Audience :: Developers
Classifier: Topic :: Software Development :: Build Tools
Classifier: Operating System :: OS Independent
